sqlcompyre/__init__.py
sqlcompyre/api.py
sqlcompyre/py.typed
sqlcompyre/analysis/__init__.py
sqlcompyre/analysis/query_inspection.py
sqlcompyre/analysis/schema_comparison.py
sqlcompyre/analysis/table_comparison.py
sqlcompyre/analysis/dialects/__init__.py
sqlcompyre/analysis/dialects/_base.py
sqlcompyre/analysis/dialects/duckdb.py
sqlcompyre/analysis/dialects/mssql.py
sqlcompyre/analysis/dialects/sqlite.py
sqlcompyre/cli/__init__.py
sqlcompyre/cli/__main__.py
sqlcompyre/config/__init__.py
sqlcompyre/config/model.py
sqlcompyre/config/validation.py
sqlcompyre/report/__init__.py
sqlcompyre/report/report.py
sqlcompyre/report/formatters/__init__.py
sqlcompyre/report/formatters/_base.py
sqlcompyre/report/formatters/_factory.py
sqlcompyre/report/formatters/terminal.py
sqlcompyre/report/formatters/text.py
sqlcompyre/report/schema/__init__.py
sqlcompyre/report/schema/schema.py
sqlcompyre/report/writers/__init__.py
sqlcompyre/report/writers/_base.py
sqlcompyre/report/writers/_factory.py
sqlcompyre/report/writers/file.py
sqlcompyre/report/writers/markdown.py
sqlcompyre/report/writers/stdout.py
sqlcompyre/results/__init__.py
sqlcompyre/results/column_matches.py
sqlcompyre/results/counts.py
sqlcompyre/results/names.py
sqlcompyre/results/row_matches.py
sqlcompyre-2.0.0.dist-info/LICENSE
sqlcompyre-2.0.0.dist-info/METADATA
sqlcompyre-2.0.0.dist-info/WHEEL
sqlcompyre-2.0.0.dist-info/entry_points.txt
sqlcompyre-2.0.0.dist-info/top_level.txt
sqlcompyre-2.0.0.dist-info/RECORD
