Metadata-Version: 2.2
Name: sqlcompyre
Version: 2.0.0
Summary: Tool for comparing and inspecting data in SQL databases.
Author-email: Oliver Borchert <oliver.borchert@quantco.com>
Project-URL: repository, https://github.com/quantco/sqlcompyre
Classifier: Programming Language :: Python :: 3
Classifier: Programming Language :: Python :: 3.11
Classifier: Programming Language :: Python :: 3.12
Classifier: Programming Language :: Python :: 3.13
Requires-Python: >=3.11
License-File: LICENSE
Requires-Dist: click
Requires-Dist: pydantic<3,>=2
Requires-Dist: pyyaml
Requires-Dist: sqlalchemy<3,>=2
Requires-Dist: tabulate
Requires-Dist: tqdm
